fuzzy_set/__init__.py
fuzzy_set/fuzzy_number.py
fuzzy_set/fuzzy_set.py
fuzzy_set/intersection.py
fuzzy_set/trapezoidal_fuzzy_number.py
fuzzy_set_nokia-0.1.2.dist-info/AUTHORS.md
fuzzy_set_nokia-0.1.2.dist-info/LICENSE
fuzzy_set_nokia-0.1.2.dist-info/METADATA
fuzzy_set_nokia-0.1.2.dist-info/WHEEL
fuzzy_set_nokia-0.1.2.dist-info/RECORD
