Metadata-Version: 2.3
Name: fuzzy-set-nokia
Version: 0.1.2
Summary: This library allows to manipulate and plot Fuzzy Sets, Fuzzy Numbers, Trapezoidal Fuzzy Numbers and Triangular Fuzzy Numbers
License: BSD-3
Author: Marc-Olivier Buob
Author-email: marc-olivier.buob@nokia-bell-labs.com
Requires-Python: >= 3.9
Classifier: Development Status :: 2 - Pre-Alpha
Classifier: Intended Audience :: Developers
Classifier: License :: OSI Approved :: Python Software Foundation License
Classifier: Natural Language :: English
Classifier: Programming Language :: Python :: 3 :: Only
Classifier: Programming Language :: Python :: 3.9
Classifier: Programming Language :: Python :: 3.10
Classifier: Programming Language :: Python :: 3.11
Classifier: Programming Language :: Python :: 3.12
Classifier: Programming Language :: Python :: 3.13
Classifier: Topic :: Documentation :: Sphinx
Requires-Dist: matplotlib (>=3.10.3)
Requires-Dist: numpy (>=1.26.1)
Requires-Dist: scipy (>=1.11.3)
